pretix_landing_pages/__init__.py
pretix_landing_pages/forms.py
pretix_landing_pages/models.py
pretix_landing_pages/signals.py
pretix_landing_pages/urls.py
pretix_landing_pages/views.py
pretix_landing_pages/locale/de/LC_MESSAGES/django.mo
pretix_landing_pages/locale/de/LC_MESSAGES/django.po
pretix_landing_pages/locale/de_Informal/.gitkeep
pretix_landing_pages/locale/de_Informal/LC_MESSAGES/django.mo
pretix_landing_pages/locale/de_Informal/LC_MESSAGES/django.po
pretix_landing_pages/migrations/0001_initial.py
pretix_landing_pages/migrations/__init__.py
pretix_landing_pages/templates/pretixplugins/pretix_landing_pages/calendar.html
pretix_landing_pages/templates/pretixplugins/pretix_landing_pages/event_list.html
pretix_landing_pages/templates/pretixplugins/pretix_landing_pages/landingpage_upload.html
pretix_landing_pages/templates/pretixplugins/pretix_landing_pages/startingpage_settings.html
pretix_landing_pages/templatetags/__init__.py
pretix_landing_pages/templatetags/load_calendar_data.py
pretix_landing_pages/templatetags/load_path.py
pretix_landing_pages-0.9.1.dist-info/LICENSE
pretix_landing_pages-0.9.1.dist-info/METADATA
pretix_landing_pages-0.9.1.dist-info/WHEEL
pretix_landing_pages-0.9.1.dist-info/entry_points.txt
pretix_landing_pages-0.9.1.dist-info/top_level.txt
pretix_landing_pages-0.9.1.dist-info/RECORD
