Metadata-Version: 2.1
Name: pretix-landing-pages
Version: 0.9.1
Summary: Custom landingpages for pretix organizers
Home-page: https://github.com/DataManagementLab/pretix-landing-pages
Author: Benjamin Haettasch & TU Darmstadt BP Informatik 2019/20 Group 45
Author-email: benjamin.haettasch@cs.tu-darmstadt.de
License: Apache Software License
Platform: UNKNOWN
Classifier: Programming Language :: Python :: 3
Classifier: License :: OSI Approved :: Apache Software License
Classifier: Operating System :: OS Independent
Classifier: Environment :: Web Environment
Classifier: Development Status :: 4 - Beta
